<?xml version="1.0" encoding="UTF-8" standalone="yes" ?>
<Root>
	<LanguageName>
		<CHS>Chinese Simplified</CHS>
	</LanguageName>
	<Languages>CHS</Languages>
	<Quest>
		<DLG_POI15_Engraved_key>
			<node1>
				<Desc>
					<CHS>你注意到这个球上的钥匙孔了吗？</CHS>
				</Desc>
			</node1>
			<node2>
				<Desc>
					<CHS>还有石头上的蚀刻和钥匙上的一样。咱们试试吧。</CHS>
				</Desc>
			</node2>
			<node3>
				<Desc>
					<CHS>真可惜我们没有钥匙。</CHS>
				</Desc>
			</node3>
			<node4>
				<Desc>
					<CHS>我希望我们有把钥匙。</CHS>
				</Desc>
			</node4>
			<node5>
				<Desc>
					<CHS>可是我们有钥匙！上面有类似的蚀刻图案。咱们试试吧。</CHS>
				</Desc>
			</node5>
			<node6>
				<Desc>
					<CHS>可是我们没有。</CHS>
				</Desc>
			</node6>
		</DLG_POI15_Engraved_key>
	</Quest>
</Root>
