<?xml version="1.0" encoding="UTF-8" standalone="yes" ?>
<Root>
	<LanguageName>
		<CHS>Chinese Simplified</CHS>
	</LanguageName>
	<Languages>CHS</Languages>
	<Quest>
		<DLG_Glass_mage>
			<node1>
				<Desc>
					<CHS>我感到这副画的附近有一个可怕的东西。就像有人在盯着我一样。</CHS>
				</Desc>
			</node1>
			<node10>
				<Desc>
					<CHS>为什么你不找个新主人？</CHS>
				</Desc>
			</node10>
			<node11>
				<Desc>
					<CHS>我的刑期结束了。命令你的大臣去获得一个灵魂权杖，然后用它把灵魂从精神苍穹里吸引出来。收获颇丰，因此他们受困的精华可以重新充满这里。</CHS>
				</Desc>
			</node11>
			<node12>
				<Desc>
					<CHS>你听说过他吗，我的臣子？</CHS>
				</Desc>
			</node12>
			<node13>
				<Desc>
					<CHS>你的故事太有趣了而令人难以忘怀。我会帮忙的。</CHS>
				</Desc>
			</node13>
			<node14>
				<Desc>
					<CHS>整个故事听上去很可疑，我们应该离开了。</CHS>
				</Desc>
			</node14>
			<node15>
				<Desc>
					<CHS>他叫我幽灵女士！我终于有昵称了!</CHS>
				</Desc>
			</node15>
			<node2>
				<Desc>
					<CHS>虽然这个宫殿在一个世纪以前就被毁掉了,但是框架上连一个泥点都没有。</CHS>
				</Desc>
			</node2>
			<node3>
				<Desc>
					<CHS>你正在看的是亚特兰提斯灵魂避难所，它几乎无法被破坏。</CHS>
				</Desc>
			</node3>
			<node4>
				<Desc>
					<CHS>我差一点跳起来了！</CHS>
				</Desc>
			</node4>
			<node5>
				<Desc>
					<CHS>我请求你的原谅，幽灵女士。那个原始的血肉之躯是你的仆人？</CHS>
				</Desc>
			</node5>
			<node6>
				<Desc>
					<CHS>如果你不介绍你自己的话，这个“原始的血肉之躯”会把你炸成碎片。</CHS>
				</Desc>
			</node6>
			<node7>
				<Desc>
					<CHS>在我将自己的灵魂安置在这个避难所里之前，我是第47任亚特兰提斯帝王的宫廷魔术师。这是在大灾难中存活下来的唯一方式。</CHS>
				</Desc>
			</node7>
			<node8>
				<Desc>
					<CHS>所以这个地方真的是传说中的亚特兰蒂斯。还有什么我需要知道的吗？</CHS>
				</Desc>
			</node8>
			<node9>
				<Desc>
					<CHS>我的避难所必须重新充能，那样我就能再活好几个世纪。</CHS>
				</Desc>
			</node9>
		</DLG_Glass_mage>
	</Quest>
</Root>
