<?xml version="1.0" encoding="UTF-8" standalone="yes" ?>
<Root>
	<LanguageName>
		<CHS>Chinese Simplified</CHS>
	</LanguageName>
	<Languages>CHS</Languages>
	<Quest>
		<DLG_POI03_Sacrifice_for_Gods1>
			<node1>
				<Desc>
					<CHS>看,一件魔法护甲！什么样的白痴会把这样的东西丢在这儿？你要拿吗？</CHS>
				</Desc>
			</node1>
			<node2>
				<Desc>
					<CHS>当然。</CHS>
				</Desc>
			</node2>
			<node3>
				<Desc>
					<CHS>让我帮你总结一下。这是一个摆放着一个疑似宗教祭品的珍贵魔法物品的古老祭坛。而我们身处波加维亚。因此不，我决不碰它。</CHS>
				</Desc>
			</node3>
		</DLG_POI03_Sacrifice_for_Gods1>
	</Quest>
</Root>
